py_gg/__init__.py
py_gg/champions.py
py_gg/stats.py
py_gg/utils.py
py_gg-2.0.2.dist-info/DESCRIPTION.rst
py_gg-2.0.2.dist-info/METADATA
py_gg-2.0.2.dist-info/RECORD
py_gg-2.0.2.dist-info/WHEEL
py_gg-2.0.2.dist-info/metadata.json
py_gg-2.0.2.dist-info/top_level.txt
