Metadata-Version: 2.0
Name: py-gg
Version: 2.0.2
Summary: A Python wrapper for the Champion.gg API
Home-page: https://github.com/solomidnet/championgg-api-python
Author: Philip Fugate
Author-email: phil.fugate@gmail.com
License: Apache 2.0
Platform: UNKNOWN
Classifier: Development Status :: 4 - Beta
Classifier: Intended Audience :: Developers
Classifier: Natural Language :: English
Classifier: Programming Language :: Python
Classifier: Programming Language :: Python :: 2.7
Classifier: Programming Language :: Python :: 3
Classifier: Programming Language :: Python :: 3.3
Classifier: Programming Language :: Python :: 3.4
Classifier: Programming Language :: Python :: 3.5
Requires-Dist: requests
